{"year":2019,"election":"ee","national":{"mandatos":21,"listas":[{"sigla":"PS","eleitos":["Pedro Manuel Dias de Jesus Marques","Maria Manuel de Lemos Leitão Marques","Manuel Pedro Cunha da Silva Pereira","Maria Margarida Ferreira Marques","André Jorge Dionísio Bradford","Sara Alexandra Rodrigues Cerdas","José Carlos das Dores Zorrinho","Maria Isabel Coelho Santos","Manuel Francisco Pizarro de Sampaio e Castro"],"nome_dr":"Partido Socialista"},{"sigla":"PPD/PSD","eleitos":["Paulo Artur dos Santos Castro de Campos Rangel","Ana Lídia Fernandes Oliveira Pereira","José Manuel Ferreira Fernandes","Maria da Graça Martins da Silva Carvalho","Álvaro dos Santos Amaro","Cláudia Sofia Gomes Monteiro de Aguiar"],"nome_dr":"Partido Social Democrata"},{"sigla":"B.E.","eleitos":["Marisa Isabel dos Santos Matias","José Guilherme Figueiredo Nobre de Gusmão"],"nome_dr":"Bloco de Esquerda"},{"sigla":"PCP-PEV","eleitos":["João Manuel Peixoto Ferreira","Sandra Maria de Brito Pereira"],"nome_dr":"CDU — Coligação Democrática Unitária"},{"sigla":"CDS-PP","eleitos":["João Nuno Lacerda Teixeira de Melo"],"sigla_dr":"CDS","nome_dr":"Partido Popular (CDS -PP)"},{"sigla":"PAN","eleitos":["Jorge Francisco Alves Vicente de Sousa Guerreiro"],"nome_dr":"Pessoas — Animais — Natureza"}]}}